initials_avatar
