Metadata-Version: 1.1
Name: initials-avatar
Version: 1.0.3
Summary: Initials Avatar for Python
Home-page: https://github.com/Brightcells/initials-avatar
Author: Hackathon
Author-email: kimi.huang@brightcells.com
License: UNKNOWN
Platform: UNKNOWN
Classifier: License :: OSI Approved :: BSD License
Classifier: Programming Language :: Python
Classifier: Programming Language :: Python :: 2.5
Classifier: Programming Language :: Python :: 2.6
Classifier: Programming Language :: Python :: 2.7
Classifier: Programming Language :: Python :: 3.2
Classifier: Programming Language :: Python :: 3.3
Classifier: Topic :: Software Development :: Libraries :: Python Modules
